CHANGELOG.md
CODE_OF_CONDUCT.md
REFERENCE.md
SECURITY.md
cloudendure/__init__.py
cloudendure/__version__.py
cloudendure/api.py
cloudendure/aws.py
cloudendure/cloudendure.py
cloudendure/cloudendure_api/__init__.py
cloudendure/cloudendure_api/api/__init__.py
cloudendure/cloudendure_api/api/account_api.py
cloudendure/cloudendure_api/api/actions_api.py
cloudendure/cloudendure_api/api/authentication_api.py
cloudendure/cloudendure_api/api/blueprint_api.py
cloudendure/cloudendure_api/api/cloud_api.py
cloudendure/cloudendure_api/api/cloud_credentials_api.py
cloudendure/cloudendure_api/api/default_api.py
cloudendure/cloudendure_api/api/licensing_api.py
cloudendure/cloudendure_api/api/machines_api.py
cloudendure/cloudendure_api/api/project_api.py
cloudendure/cloudendure_api/api/recovery_plans_api.py
cloudendure/cloudendure_api/api/replication_api.py
cloudendure/cloudendure_api/api/user_api.py
cloudendure/cloudendure_api/api_client.py
cloudendure/cloudendure_api/configuration.py
cloudendure/cloudendure_api/models/__init__.py
cloudendure/cloudendure_api/models/cloud_endure_account.py
cloudendure/cloudendure_api/models/cloud_endure_account_request.py
cloudendure/cloudendure_api/models/cloud_endure_account_request_list.py
cloudendure/cloudendure_api/models/cloud_endure_accounts_list.py
cloudendure/cloudendure_api/models/cloud_endure_agent_next_replication_init_request.py
cloudendure/cloudendure_api/models/cloud_endure_all_project_features.py
cloudendure/cloudendure_api/models/cloud_endure_audit_log.py
cloudendure/cloudendure_api/models/cloud_endure_audit_log_changed_field.py
cloudendure/cloudendure_api/models/cloud_endure_audit_log_entry.py
cloudendure/cloudendure_api/models/cloud_endure_bandwidth_throttling.py
cloudendure/cloudendure_api/models/cloud_endure_blueprint.py
cloudendure/cloudendure_api/models/cloud_endure_blueprint_list.py
cloudendure/cloudendure_api/models/cloud_endure_cloud.py
cloudendure/cloudendure_api/models/cloud_endure_cloud_credentials.py
cloudendure-0.3.5.dist-info/entry_points.txt
cloudendure-0.3.5.dist-info/LICENSE
cloudendure-0.3.5.dist-info/WHEEL
cloudendure-0.3.5.dist-info/METADATA
cloudendure-0.3.5.dist-info/RECORD
