Metadata-Version: 2.1
Name: cloudendure
Version: 0.3.5
Summary: Python wrapper and CLI for CloudEndure
Home-page: https://2ndwatch.github.io/cloudendure-python/
Author: Mark Beacom
Author-email: mark@markbeacom.com
Maintainer: Evan Lucchesi
Maintainer-email: evan@2ndwatch.com
Requires-Python: >=3.7,<4.0
Classifier: Environment :: Console
Classifier: Environment :: MacOS X
Classifier: Environment :: Win32 (MS Windows)
Classifier: License :: OSI Approved :: MIT License
Classifier: Natural Language :: English
Classifier: Operating System :: MacOS
Classifier: Operating System :: MacOS :: MacOS 9
Classifier: Operating System :: MacOS :: MacOS X
Classifier: Operating System :: Microsoft
Classifier: Operating System :: Microsoft :: MS-DOS
Classifier: Operating System :: Microsoft :: Windows
Classifier: Operating System :: Microsoft :: Windows :: Windows 10
Classifier: Operating System :: Microsoft :: Windows :: Windows 7
Classifier: Operating System :: Microsoft :: Windows :: Windows 8
Classifier: Operating System :: Microsoft :: Windows :: Windows 8.1
Classifier: Operating System :: Microsoft :: Windows :: Windows Server 2008
Classifier: Operating System :: POSIX :: Linux
Classifier: Programming Language :: Python
Classifier: Programming Language :: Python :: 3
Classifier: Programming Language :: Python :: 3 :: Only
Classifier: Programming Language :: Python :: 3.7
Classifier: Programming Language :: Python :: 3.8
Classifier: Programming Language :: Python :: 3.9
Classifier: Programming Language :: Python :: Implementation :: CPython
Classifier: Topic :: Internet
Classifier: Topic :: Internet :: WWW/HTTP
Classifier: Topic :: Internet :: WWW/HTTP :: Session
Classifier: Topic :: Software Development :: Libraries
Classifier: Topic :: Software Development :: Libraries :: Python Modules
Classifier: Topic :: Software Development :: User Interfaces
Classifier: Topic :: Utilities
Requires-Dist: boto3 (>=1.12.30,<2.0.0)
Requires-Dist: certifi (>=2019.11.28,<2020.0.0)
Requires-Dist: cookiecutter (>=1.7.0,<2.0.0)
Requires-Dist: fire (>=0.3.0,<0.4.0)
Requires-Dist: python-dateutil (>=2.8.1,<3.0.0)
Requires-Dist: requests (>=2.23.0,<3.0.0)
Requires-Dist: setuptools (>=45.2.0,<46.0.0)
Requires-Dist: six (>=1.14.0,<2.0.0)
Requires-Dist: urllib3 (>=1.25.8,<2.0.0)
Project-URL: Repository, https://github.com/2ndWatch/cloudendure-python
